<?xml version="1.0" encoding="utf-8" ?>
<dwsync>
<file name="bootstrap.html" server="www.pavas.co/tlab/" local="131083177580000000" remote="131203484400000000" Dst="0" />
<file name="foundation.html" server="www.pavas.co/tlab/" local="131083177580000000" remote="131203484400000000" Dst="0" />
<file name="index.html" server="www.pavas.co/tlab/" local="131083177580000000" remote="131203484400000000" Dst="0" />
<file name="jqueryui.html" server="www.pavas.co/tlab/" local="131083177580000000" remote="131203484400000000" Dst="0" />
<file name="bootstrap.html" server="www.pavas.co/TLAB1.0/" local="131314664257253382" remote="131314335000000000" Dst="0" />
<file name="index.html" server="www.pavas.co/TLAB1.0/" local="131314664262879628" remote="131314335000000000" Dst="0" />
<file name="foundation.html" server="www.pavas.co/TLAB1.0/" local="131314664262944516" remote="131314335000000000" Dst="0" />
<file name="jqueryui.html" server="www.pavas.co/TLAB1.0/" local="131314664267681220" remote="131314335000000000" Dst="0" />
<file name="bootstrap.html" server="www.pavas.com.co/httpdocs/TLAB1.0/" local="131314664257253382" remote="131342227800000000" Dst="0" />
<file name="foundation.html" server="www.pavas.com.co/httpdocs/TLAB1.0/" local="131314664262944516" remote="131342227800000000" Dst="0" />
<file name="index.html" server="www.pavas.com.co/httpdocs/TLAB1.0/" local="131314664262879628" remote="131342227800000000" Dst="0" />
<file name="jqueryui.html" server="www.pavas.com.co/httpdocs/TLAB1.0/" local="131314664267681220" remote="131342227800000000" Dst="0" />
<file name="bootstrap.html" server="www.pavas.com.co/httpdocs/m2/" local="131314664257253382" remote="131346837000000000" Dst="0" />
<file name="index.html" server="www.pavas.com.co/httpdocs/m2/" local="131314664262879628" remote="131346837000000000" Dst="0" />
<file name="foundation.html" server="www.pavas.com.co/httpdocs/m2/" local="131314664262944516" remote="131346837000000000" Dst="0" />
<file name="jqueryui.html" server="www.pavas.com.co/httpdocs/m2/" local="131314664267681220" remote="131346837000000000" Dst="0" />
<file name="bootstrap.html" server="www.pavas.com.co/httpdocs/CS/" local="131314664257253382" remote="131394750000000000" Dst="0" />
<file name="foundation.html" server="www.pavas.com.co/httpdocs/CS/" local="131314664262944516" remote="131394750000000000" Dst="0" />
<file name="index.html" server="www.pavas.com.co/httpdocs/CS/" local="131314664262879628" remote="131394750000000000" Dst="0" />
<file name="jqueryui.html" server="www.pavas.com.co/httpdocs/CS/" local="131314664267681220" remote="131394750000000000" Dst="0" />
</dwsync>